README
setup.py
moodle_ws_client/__init__.py
moodle_ws_client/moodle.py
moodle_ws_client.egg-info/PKG-INFO
moodle_ws_client.egg-info/SOURCES.txt
moodle_ws_client.egg-info/dependency_links.txt
moodle_ws_client.egg-info/not-zip-safe
moodle_ws_client.egg-info/top_level.txt