Metadata-Version: 1.1
Name: moodle-ws-client
Version: 0.0.2
Summary: Moodle web services (2.5) connection library 
Home-page: https://github.com/kotejante/python-moodle
Author: Francisco Moreno
Author-email: packo@assamita.net
License: GNU Affero General Public License v3
Platform: any
Classifier: Development Status :: 4 - Beta
Classifier: Environment :: Web Environment
Classifier: Intended Audience :: Developers
Classifier: License :: OSI Approved :: GNU Affero General Public License v3
Classifier: Operating System :: OS Independent
Classifier: Programming Language :: Python
Classifier: Topic :: Internet :: WWW/HTTP :: Dynamic Content
Classifier: Topic :: Software Development :: Libraries :: Python Modules
